sip/__init__.py
sip/__meta__.py
sip/core.py
streamlit_infinite_pages-0.1.1.dist-info/LICENSE
streamlit_infinite_pages-0.1.1.dist-info/METADATA
streamlit_infinite_pages-0.1.1.dist-info/WHEEL
streamlit_infinite_pages-0.1.1.dist-info/RECORD
