Metadata-Version: 2.1
Name: streamlit-infinite-pages
Version: 0.1.1
Summary: Streamlit wrapper to add simple support for an arbitrary number of pages.
License: MIT
Author: Hart Traveller
Author-email: ruling_fiction.0b@icloud.com
Requires-Python: >=3.10,<4.0
Classifier: License :: OSI Approved :: MIT License
Classifier: Programming Language :: Python :: 3
Classifier: Programming Language :: Python :: 3.10
Classifier: Programming Language :: Python :: 3.11
Classifier: Programming Language :: Python :: 3.12
Requires-Dist: streamlit (==1.37.1)
Requires-Dist: watchdog (>=4.0.0,<5.0.0)
